LICENSE
MANIFEST.in
README
setup.py
fedex/__init__.py
fedex/config.py
fedex/tests.py
fedex.py.egg-info/PKG-INFO
fedex.py.egg-info/SOURCES.txt
fedex.py.egg-info/dependency_links.txt
fedex.py.egg-info/requires.txt
fedex.py.egg-info/top_level.txt
fedex/services/__init__.py
fedex/services/addresses.py
fedex/services/commons.py
fedex/services/rates.py
fedex/services/shipments.py
fedex/services/tracking.py
fedex/wsdls/ASYNCService_v3.wsdl
fedex/wsdls/AddressValidationService_v4.wsdl
fedex/wsdls/CloseService_v4.wsdl
fedex/wsdls/CountryService_v4.wsdl
fedex/wsdls/LocationsService_v3.wsdl
fedex/wsdls/OpenShipService_v9.wsdl
fedex/wsdls/PickupService_v11.wsdl
fedex/wsdls/RateService_v18.wsdl
fedex/wsdls/ShipService_v17.wsdl
fedex/wsdls/TrackService_v10.wsdl
fedex/wsdls/UploadDocumentService_v8.wsdl
fedex/wsdls/ValidationAvailabilityAndCommitmentService_v4.wsdl
fedex/wsdls/beta/ASYNCService_v3.wsdl
fedex/wsdls/beta/AddressValidationService_v4.wsdl
fedex/wsdls/beta/CloseService_v4.wsdl
fedex/wsdls/beta/CountryService_v4.wsdl
fedex/wsdls/beta/LocationsService_v3.wsdl
fedex/wsdls/beta/OpenShipService_v9.wsdl
fedex/wsdls/beta/PickupService_v11.wsdl
fedex/wsdls/beta/RateService_v18.wsdl
fedex/wsdls/beta/ShipService_v17.wsdl
fedex/wsdls/beta/TrackService_v10.wsdl
fedex/wsdls/beta/UploadDocumentService_v8.wsdl
fedex/wsdls/beta/ValidationAvailabilityAndCommitmentService_v4.wsdl