Metadata-Version: 1.0
Name: fedex.py
Version: 1.0.0
Summary: FedEx API for Python.
Home-page: http://github.com/jzempel/fedex
Author: Jonathan Zempel
Author-email: jzempel@gmail.com
License: BSD
Platform: UNKNOWN
